pepita/__init__.py
pepita/exoInfoMatrix.py
pepita-0.0.2.dist-info/METADATA
pepita-0.0.2.dist-info/WHEEL
pepita-0.0.2.dist-info/licenses/LICENSE
pepita-0.0.2.dist-info/RECORD
