Metadata-Version: 2.1
Name: pepita
Version: 0.0.2
Summary: Predict the precision of exoplanet parameters from transit light-curves using information analysis techniques.
Project-URL: Homepage, https://github.com/JulioHC00/PEPITA
Project-URL: Bug Tracker, https://github.com/JulioHC00/PEPITA/issues
Author-email: Julio Hernandez Camero <julhcam@pm.me>
License: MIT License
License-File: LICENSE
Keywords: analysis,exoplanets,lightcurve,transits
Classifier: License :: OSI Approved :: MIT License
Classifier: Operating System :: OS Independent
Classifier: Programming Language :: Python :: 3
Requires-Python: >=3.7
Requires-Dist: exoplanet
Requires-Dist: matplotlib
Requires-Dist: numpy
Requires-Dist: pymc3
